mcp_image_reader/__init__.py
mcp_image_reader/image_processor.py
mcp_image_reader/py.typed
mcp_image_reader/server.py
mcp_image_reader-0.1.4.dist-info/licenses/LICENSE
mcp_image_reader-0.1.4.dist-info/METADATA
mcp_image_reader-0.1.4.dist-info/WHEEL
mcp_image_reader-0.1.4.dist-info/entry_points.txt
mcp_image_reader-0.1.4.dist-info/top_level.txt
mcp_image_reader-0.1.4.dist-info/RECORD
