Metadata-Version: 2.4
Name: mcp-image-reader
Version: 0.1.4
Summary: MCP server for reading and analyzing images with OCR and AI vision capabilities
Author-email: MCP Image Reader Contributors <mcp-image-reader@example.com>
License-Expression: MIT
Project-URL: Homepage, https://github.com/thanhma/mcp-image-reader
Project-URL: Repository, https://github.com/thanhma/mcp-image-reader.git
Project-URL: Issues, https://github.com/thanhma/mcp-image-reader/issues
Project-URL: Documentation, https://github.com/thanhma/mcp-image-reader#readme
Keywords: mcp,ocr,image,vision,ai,tesseract,server
Classifier: Development Status :: 4 - Beta
Classifier: Intended Audience :: Developers
Classifier: Operating System :: OS Independent
Classifier: Programming Language :: Python :: 3
Classifier: Programming Language :: Python :: 3.8
Classifier: Programming Language :: Python :: 3.9
Classifier: Programming Language :: Python :: 3.10
Classifier: Programming Language :: Python :: 3.11
Classifier: Programming Language :: Python :: 3.12
Classifier: Topic :: Scientific/Engineering :: Image Processing
Classifier: Topic :: Text Processing :: Linguistic
Classifier: Topic :: Software Development :: Libraries :: Python Modules
Requires-Python: >=3.8
License-File: LICENSE
Requires-Dist: mcp>=1.0.0
Requires-Dist: pillow>=10.0.0
Requires-Dist: pytesseract>=0.3.10
Requires-Dist: opencv-python>=4.8.0
Requires-Dist: numpy<3.0.0,>=1.24.0
Requires-Dist: pandas>=2.0.0
Requires-Dist: cairosvg>=2.7.0
Requires-Dist: svglib>=1.5.0
Provides-Extra: dev
Requires-Dist: pytest>=7.0.0; extra == "dev"
Requires-Dist: black>=23.0.0; extra == "dev"
Requires-Dist: isort>=5.12.0; extra == "dev"
Requires-Dist: mypy>=1.5.0; extra == "dev"
Requires-Dist: build>=0.10.0; extra == "dev"
Requires-Dist: twine>=4.0.0; extra == "dev"
Dynamic: license-file
